genai_hub_serve/__init__.py
genai_hub_serve/huggingface/__init__.py
genai_hub_serve/huggingface/serve_auto_seq2seq_lm.py
genai_hub_serve/semantix_kserve.py
genai_hub_serve-0.0.1.dist-info/LICENSE.txt
genai_hub_serve-0.0.1.dist-info/WHEEL
genai_hub_serve-0.0.1.dist-info/METADATA
genai_hub_serve-0.0.1.dist-info/RECORD
